README
setup.cfg
setup.py
avalanche/__init__.py
avalanche/core.py
avalanche/params.py
avalanche/renderer.py
avalanche/router.py
avalanche.egg-info/PKG-INFO
avalanche.egg-info/SOURCES.txt
avalanche.egg-info/dependency_links.txt
avalanche.egg-info/requires.txt
avalanche.egg-info/top_level.txt