Metadata-Version: 1.1
Name: avalanche
Version: 0.3.0
Summary: Web Framework with a focus on testability and reusability
Home-page: http://packages.python.org/avalanche/overview.html
Author: Eduardo Naufel Schettino
Author-email: schettino72@gmail.com
License: MIT
Platform: UNKNOWN
Classifier: Development Status :: 4 - Beta
Classifier: Environment :: Web Environment
Classifier: License :: OSI Approved :: MIT License
Classifier: Natural Language :: English
Classifier: Programming Language :: Python :: 3
Classifier: Programming Language :: Python :: 3.3
Classifier: Intended Audience :: Developers
Classifier: Topic :: Internet :: WWW/HTTP
Classifier: Topic :: Software Development :: Libraries :: Application Frameworks
Classifier: Topic :: Software Development :: Libraries :: Python Modules
